Metadata-Version: 2.4
Name: pybmesh
Version: 1.0.3
Summary: Block Mesh processing library for OpenFOAM
Home-page: https://gitlab.com/alexis.sauvageon/pybmesh.git
Author: Alexis Sauvageon
Author-email: Alexis Sauvageon <alexis.sauvageon@arep.fr>
Project-URL: homepage, https://gitlab.com/alexis.sauvageon/pybmesh.git
Keywords: mesh,geometry,openfoam
Classifier: Development Status :: 5 - Production/Stable
Classifier: Intended Audience :: Developers
Classifier: Programming Language :: Python :: 3
Classifier: Programming Language :: Python :: 3.11
Requires-Python: >=3.11
License-File: LICENSE
Requires-Dist: Cython==3.0.12
Requires-Dist: gmsh==4.13.1
Requires-Dist: matplotlib==3.10.1
Requires-Dist: numpy==2.2.3
Requires-Dist: pandas==2.2.2
Requires-Dist: pyside6==6.9.0
Requires-Dist: scikit_learn==1.6.1
Requires-Dist: scikit-spatial==8.1.0
Requires-Dist: scipy==1.15.2
Requires-Dist: vtk==9.3.1
Dynamic: author
Dynamic: home-page
Dynamic: license-file
